cli.py
lib/api/abstract_client.py
lib/api/gitea.py
lib/api/gitee.py
lib/api/github.py
lib/api/index.py
lib/handler/helper.py
lib/handler/init.py
lib/handler/remote.py
lib/handler/sync.py
lib/http.py
lib/logger.py
lib/model/config.py
lib/model/opts.py
lib/model/repo.py
lib/model/sync.py
lib/util.py
lib/util_git.py
lib/version.py
pyproject.toml
trident_sync-1.2.3.dist-info/entry_points.txt
trident_sync-1.2.3.dist-info/LICENSE
trident_sync-1.2.3.dist-info/METADATA
trident_sync-1.2.3.dist-info/WHEEL
trident_sync-1.2.3.dist-info/RECORD
