Metadata-Version: 2.1
Name: trident-sync
Version: 1.2.3
Summary: 三叉戟，二次开发项目同步升级工具，Secondary development repo sync and upgrade CLI
License: MIT
Author: xiaojunnuo
Author-email: xiaojunnuo@qq.com
Requires-Python: >=3.8,<4
Classifier: License :: OSI Approved :: MIT License
Classifier: Programming Language :: Python :: 3
Classifier: Programming Language :: Python :: 3.8
Classifier: Programming Language :: Python :: 3.9
Classifier: Programming Language :: Python :: 3.10
Classifier: Programming Language :: Python :: 3.11
Requires-Dist: docopt (>=0.6.2,<0.7.0)
Requires-Dist: gitpython (>=3.1.30,<4.0.0)
Requires-Dist: loguru (>=0.6.0,<0.7.0)
Requires-Dist: pyyaml (>=6.0,<7.0)
Requires-Dist: requests (>=2.28.2,<3.0.0)
